fonoapi/__init__.py
fonoapi/fonoapi.py
fonoapi/version.py
fonoapi-0.1.4.dist-info/LICENSE
fonoapi-0.1.4.dist-info/METADATA
fonoapi-0.1.4.dist-info/WHEEL
fonoapi-0.1.4.dist-info/top_level.txt
fonoapi-0.1.4.dist-info/RECORD
