Metadata-Version: 2.1
Name: fonoapi
Version: 0.1.4
Summary: Access Freshpixl's Fono Api to gain insight into mobile phones
Home-page: https://github.com/jakesherman/fonoapi
Author: shakee93, jesusperiago, jakesherman
Author-email: jake@jakesherman.com
License: MIT License
Download-URL: https://github.com/jakesherman/fonoapi/archive/v0.1.4.tar.gz
Keywords: api,mobile,phone,FonoApi
Platform: UNKNOWN
Requires-Dist: numpy (>=1.10)
Requires-Dist: pandas (>=0.20.0)
Requires-Dist: pytest (>=3.1.0)
Requires-Dist: requests (>=2.18.0)
